xlsx_template/__init__.py
xlsx_template/code_generator.py
xlsx_template/consts.py
xlsx_template/environment.py
xlsx_template/exceptions.py
xlsx_template/file_system_loader.py
xlsx_template/filters.py
xlsx_template/grammar.py
xlsx_template/nodes.py
xlsx_template/parser.py
xlsx_template/runtime/__init__.py
xlsx_template/runtime/cell_groups.py
xlsx_template/runtime/context.py
xlsx_template/runtime/loop_context.py
xlsx_template/template.py
xlsx_template/utils.py
xlsx_template-0.1.2.dist-info/WHEEL
xlsx_template-0.1.2.dist-info/METADATA
xlsx_template-0.1.2.dist-info/RECORD
