Metadata-Version: 2.1
Name: xlsx-template
Version: 0.1.2
Summary: 
Author: Sergei Sinitsyn
Author-email: sinitsinsv@gmail.com
Requires-Python: >=3.7
Classifier: Programming Language :: Python :: 3
Classifier: Programming Language :: Python :: 3.7
Classifier: Programming Language :: Python :: 3.8
Classifier: Programming Language :: Python :: 3.9
Requires-Dist: cached-property (>=1.5.2,<2.0.0)
Requires-Dist: openpyxl (>=3.0.5,<4.0.0)
Requires-Dist: pyparsing (>=2.4.7,<3.0.0)
